{
  "openapi": "3.0.1",
  "info": {
    "title": "Api",
    "version": "1.0"
  },
  "paths": {
    "/api/Auth/Login": {
      "post": {
        "tags": [
          "Auth"
        ],
        "requestBody": {
          "content": {
            "application/json": {
              "schema": {
                "$ref": "#/components/schemas/LoginVm"
              }
            },
            "text/json": {
              "schema": {
                "$ref": "#/components/schemas/LoginVm"
              }
            },
            "application/*+json": {
              "schema": {
                "$ref": "#/components/schemas/LoginVm"
              }
            }
          }
        },
        "responses": {
          "200": {
            "description": "OK"
          }
        }
      }
    },
    "/api/Auth/Register": {
      "post": {
        "tags": [
          "Auth"
        ],
        "requestBody": {
          "content": {
            "application/json": {
              "schema": {
                "$ref": "#/components/schemas/RegisterdVm"
              }
            },
            "text/json": {
              "schema": {
                "$ref": "#/components/schemas/RegisterdVm"
              }
            },
            "application/*+json": {
              "schema": {
                "$ref": "#/components/schemas/RegisterdVm"
              }
            }
          }
        },
        "responses": {
          "200": {
            "description": "OK"
          }
        }
      }
    }
  },
  "components": {
    "schemas": {
      "LoginVm": {
        "type": "object",
        "properties": {
          "email": {
            "type": "string",
            "nullable": true
          },
          "password": {
            "type": "string",
            "nullable": true
          }
        },
        "additionalProperties": false
      },
      "RegisterdVm": {
        "type": "object",
        "properties": {
          "email": {
            "type": "string",
            "nullable": true
          },
          "username": {
            "type": "string",
            "nullable": true
          },
          "password": {
            "type": "string",
            "nullable": true
          },
          "userRole": {
            "$ref": "#/components/schemas/UserRole"
          }
        },
        "additionalProperties": false
      },
      "UserRole": {
        "enum": [
          0,
          1,
          2
        ],
        "type": "integer",
        "format": "int32"
      }
    }
  }
}